check_numbers.py
Check_Numbers-1.0.7.dist-info/LICENSE
Check_Numbers-1.0.7.dist-info/METADATA
Check_Numbers-1.0.7.dist-info/WHEEL
Check_Numbers-1.0.7.dist-info/top_level.txt
Check_Numbers-1.0.7.dist-info/RECORD
